{
  "version": "6",
  "dialect": "sqlite",
  "id": "ce8230bf-647e-4a46-ab0b-37833a8177a5",
  "prevId": "00000000-0000-0000-0000-000000000000",
  "tables": {
    "images": {
      "name": "images",
      "columns": {
        "id": {
          "name": "id",
          "type": "text",
          "primaryKey": true,
          "notNull": true,
          "autoincrement": false
        }
      },
      "indexes": {},
      "foreignKeys": {},
      "compositePrimaryKeys": {},
      "uniqueConstraints": {},
      "checkConstraints": {}
    },
    "projects": {
      "name": "projects",
      "columns": {
        "id": {
          "name": "id",
          "type": "text",
          "primaryKey": true,
          "notNull": true,
          "autoincrement": false
        },
        "title": {
          "name": "title",
          "type": "text",
          "primaryKey": false,
          "notNull": true,
          "autoincrement": false
        },
        "title_fr": {
          "name": "title_fr",
          "type": "text",
          "primaryKey": false,
          "notNull": true,
          "autoincrement": false
        },
        "description": {
          "name": "description",
          "type": "text",
          "primaryKey": false,
          "notNull": true,
          "autoincrement": false
        },
        "description_fr": {
          "name": "description_fr",
          "type": "text",
          "primaryKey": false,
          "notNull": true,
          "autoincrement": false
        },
        "slug": {
          "name": "slug",
          "type": "text",
          "primaryKey": false,
          "notNull": true,
          "autoincrement": false
        },
        "slug_fr": {
          "name": "slug_fr",
          "type": "text",
          "primaryKey": false,
          "notNull": true,
          "autoincrement": false
        },
        "cover": {
          "name": "cover",
          "type": "text",
          "primaryKey": false,
          "notNull": true,
          "autoincrement": false
        },
        "created_at": {
          "name": "created_at",
          "type": "text",
          "primaryKey": false,
          "notNull": true,
          "autoincrement": false
        },
        "updated_at": {
          "name": "updated_at",
          "type": "text",
          "primaryKey": false,
          "notNull": true,
          "autoincrement": false
        }
      },
      "indexes": {
        "projects_title_unique": {
          "name": "projects_title_unique",
          "columns": [
            "title"
          ],
          "isUnique": true
        },
        "projects_title_fr_unique": {
          "name": "projects_title_fr_unique",
          "columns": [
            "title_fr"
          ],
          "isUnique": true
        },
        "projects_slug_unique": {
          "name": "projects_slug_unique",
          "columns": [
            "slug"
          ],
          "isUnique": true
        },
        "projects_slug_fr_unique": {
          "name": "projects_slug_fr_unique",
          "columns": [
            "slug_fr"
          ],
          "isUnique": true
        }
      },
      "foreignKeys": {},
      "compositePrimaryKeys": {},
      "uniqueConstraints": {},
      "checkConstraints": {}
    }
  },
  "views": {},
  "enums": {},
  "_meta": {
    "schemas": {},
    "tables": {},
    "columns": {}
  },
  "internal": {
    "indexes": {}
  }
}